wrapcolor/__init__.py
wrapcolor/color.py
wrapcolor-0.1.4.dist-info/licenses/LICENSE
wrapcolor-0.1.4.dist-info/METADATA
wrapcolor-0.1.4.dist-info/WHEEL
wrapcolor-0.1.4.dist-info/top_level.txt
wrapcolor-0.1.4.dist-info/RECORD
