Metadata-Version: 2.4
Name: wrapcolor
Version: 0.1.4
Summary: Universal ANSI colorizer for Python (8/16 colors, 256-color, RGB, styles)
Home-page: https://github.com/datsiuk7/wrapcolor
Author: Bohdan
Author-email: datcukbogdan@gmail.com
License: MIT
Project-URL: Homepage, https://github.com/datsiuk7/wrapcolor
Project-URL: Source, https://github.com/datsiuk7/wrapcolor
Project-URL: Issues, https://github.com/datsiuk7/wrapcolor/issues
Keywords: ansi,color,terminal,console,rgb,xterm-256,styles
Classifier: Development Status :: 4 - Beta
Classifier: Intended Audience :: Developers
Classifier: Environment :: Console
Classifier: License :: OSI Approved :: MIT License
Classifier: Operating System :: OS Independent
Classifier: Programming Language :: Python :: 3
Classifier: Topic :: Terminals
Classifier: Topic :: Text Processing :: General
Classifier: Topic :: Utilities
Requires-Python: >=3.10
License-File: LICENSE
Dynamic: author
Dynamic: author-email
Dynamic: classifier
Dynamic: description
Dynamic: description-content-type
Dynamic: home-page
Dynamic: keywords
Dynamic: license
Dynamic: license-file
Dynamic: project-url
Dynamic: requires-python
Dynamic: summary
